CHANGES.rst
CONTRIBUTORS.rst
DEVELOP.rst
DEVELOP_THEME.rst
LICENSE.GPL
LICENSE.rst
MANIFEST.in
README.rst
setup.cfg
setup.py
docs/index.rst
src/theme/__init__.py
src/theme.habas34.egg-info/PKG-INFO
src/theme.habas34.egg-info/SOURCES.txt
src/theme.habas34.egg-info/dependency_links.txt
src/theme.habas34.egg-info/entry_points.txt
src/theme.habas34.egg-info/namespace_packages.txt
src/theme.habas34.egg-info/not-zip-safe
src/theme.habas34.egg-info/requires.txt
src/theme.habas34.egg-info/top_level.txt
src/theme/habas34/__init__.py
src/theme/habas34/configure.zcml
src/theme/habas34/interfaces.py
src/theme/habas34/permissions.zcml
src/theme/habas34/setuphandlers.py
src/theme/habas34/testing.py
src/theme/habas34/upgrades.py
src/theme/habas34/upgrades.zcml
src/theme/habas34/browser/__init__.py
src/theme/habas34/browser/configure.zcml
src/theme/habas34/browser/overrides/.gitkeep
src/theme/habas34/browser/static/.gitkeep
src/theme/habas34/locales/README.rst
src/theme/habas34/locales/__init__.py
src/theme/habas34/locales/theme.habas34.pot
src/theme/habas34/locales/update.py
src/theme/habas34/locales/update.sh
src/theme/habas34/locales/en/LC_MESSAGES/theme.habas34.po
src/theme/habas34/profiles/default/browserlayer.xml
src/theme/habas34/profiles/default/catalog.xml
src/theme/habas34/profiles/default/metadata.xml
src/theme/habas34/profiles/default/registry.xml
src/theme/habas34/profiles/default/rolemap.xml
src/theme/habas34/profiles/default/theme.xml
src/theme/habas34/profiles/uninstall/browserlayer.xml
src/theme/habas34/profiles/uninstall/theme.xml
src/theme/habas34/tests/__init__.py
src/theme/habas34/tests/test_robot.py
src/theme/habas34/tests/test_setup.py
src/theme/habas34/tests/robot/test_example.robot
src/theme/habas34/theme/backend.xml
src/theme/habas34/theme/barceloneta-apple-touch-icon-114x114-precomposed.png
src/theme/habas34/theme/barceloneta-apple-touch-icon-144x144-precomposed.png
src/theme/habas34/theme/barceloneta-apple-touch-icon-57x57-precomposed.png
src/theme/habas34/theme/barceloneta-apple-touch-icon-72x72-precomposed.png
src/theme/habas34/theme/barceloneta-apple-touch-icon-precomposed.png
src/theme/habas34/theme/barceloneta-apple-touch-icon.png
src/theme/habas34/theme/barceloneta-favicon.ico
src/theme/habas34/theme/index.html
src/theme/habas34/theme/manifest.cfg
